[
  {
    "title": "Security",
    "skills": [
      {
        "title": "Web Application Auditing",
        "details": "Burpsuite, OWASP ZAP, ffuf, w3af"
      },
      {
        "title": "Network Security",
        "details": "firewalls, various IDS/IPSs, VPNs, snort, suricata, CrowdSec, iptables, ufw"
      },
      {
        "title": "Enumeration",
        "details": "nmap, dirbuster/gobuster, amass, various OSINT methods"
      },
      {
        "title": "Vulnerability Assessment and Management",
        "details": "nuclei, Nessus, Nikto, OpenVAS, WireShark"
      },
      {
        "title": "Adversary Simulation",
        "details": "metasploit, armitage, cobalt strike"
      }
    ]
  },
  {
    "title": "DevOps",
    "skills": [
      {
        "title": "Provisioning",
        "details": "Ansible, fabric"
      },
      {
        "title": "Containerization",
        "details": "Docker, Podman, Vagrant, k8s"
      },
      {
        "title": "CI/CD",
        "details": "Jenkins, TeamCity CI, Gitlab CI, Fastlane, GitHub Actions"
      },
      {
        "title": "Monitoring",
        "details": "Prometheus, Grafana, Graylog"
      },
      {
        "title": "Security SAST",
        "details": "trivy, njsscan, hadolint"
      },
      {
        "title": "Security DAST",
        "details": "OWASP ZAP, Selenium, nuclei"
      },
      {
        "title": "AWS",
        "details": ""
      }
    ]
  },
  {
    "title": "Frontend",
    "skills": [
      {
        "title": "HTML",
        "details": "HTML5, semantic HTML"
      },
      {
        "title": "CSS",
        "details": "SASS/SCSS, BEM methodology"
      },
      {
        "title": "JavaScript",
        "details": "ES6+, Jest, Cypress, Webpack, jQuery"
      },
      {
        "title": "React",
        "details": "Redux, MobX, Zustand, Saga, Reselect, React Query, etc."
      },
      {
        "title": "React Native",
        "details": "React Native CLI, Expo CLI, Detox"
      }
    ]
  },
  {
    "title": "Backend",
    "skills": [
      {
        "title": "PHP",
        "details": "Laravel, phpunit, phpdoc, Swagger (OpenAPI)"
      },
      {
        "title": "NodeJS",
        "details": "Express.js"
      },
      {
        "title": "Python",
        "details": "Flask, Django, FastAPI"
      },
      {
        "title": "MySQL, MariaDB, MongoDB, ClickHouse",
        "details": ""
      }
    ]
  },
  {
    "title": "Other",
    "skills": [
      {
        "title": "Git",
        "details": ""
      },
      {
        "title": "Shell",
        "details": "sh, bash, zsh, python, make"
      },
      {
        "title": "Brainfuck",
        "details": "esoteric programming language"
      }
    ]
  }
]
